graphus/__init__.py
graphus/client.py
graphus/color_types.py
graphus/node.py
graphus/node_type.py
graphus/response.py
graphus/utils.py
graphus-0.1.2.dist-info/LICENSE
graphus-0.1.2.dist-info/METADATA
graphus-0.1.2.dist-info/WHEEL
graphus-0.1.2.dist-info/entry_points.txt
graphus-0.1.2.dist-info/RECORD
