Metadata-Version: 2.1
Name: graphus
Version: 0.1.2
Summary: Graphus is a dynamic GraphQL client that generates its API objects and methods dynamically by parsing GraphQL Schemas.
Home-page: https://github.com/IonesioJunior/Graphus
License: Apache-2.0
Author: Ionesio Junior
Author-email: ionesiojr@gmail.com
Requires-Python: >=3.10,<4.0
Classifier: License :: OSI Approved :: Apache Software License
Classifier: Programming Language :: Python :: 3
Classifier: Programming Language :: Python :: 3.10
Classifier: Programming Language :: Python :: 3.11
Provides-Extra: test
Requires-Dist: graphql-core (>=3.2.3,<4.0.0)
Project-URL: Documentation, https://ionesiojunior.github.io/Graphus/
Project-URL: Repository, https://github.com/IonesioJunior/Graphus
